finesm/__init__.py
finesm-1.0.0.dist-info/LICENSE
finesm-1.0.0.dist-info/METADATA
finesm-1.0.0.dist-info/WHEEL
finesm-1.0.0.dist-info/top_level.txt
finesm-1.0.0.dist-info/RECORD
